cad_to_shapely/__init__.py
cad_to_shapely/cadimporter.py
cad_to_shapely/dxf.py
cad_to_shapely/examples.py
cad_to_shapely/geometry.py
cad_to_shapely/svg.py
cad_to_shapely/test_cad_to_shapely.py
cad_to_shapely/utils.py
cad_to_shapely-0.3.2.dist-info/LICENSE
cad_to_shapely-0.3.2.dist-info/METADATA
cad_to_shapely-0.3.2.dist-info/WHEEL
cad_to_shapely-0.3.2.dist-info/top_level.txt
cad_to_shapely-0.3.2.dist-info/RECORD
