Metadata-Version: 2.1
Name: cad_to_shapely
Version: 0.3.2
Summary: Import CAD files to Shapely geometry
Home-page: https://github.com/aegis1980/cad_to_shapely
Author: Jon Robinson
Author-email: jonrobinson1980@gmail.com
License: MIT
Classifier: Development Status :: 3 - Alpha
Classifier: Intended Audience :: Science/Research
Classifier: License :: OSI Approved :: MIT License
Classifier: Programming Language :: Python :: 3 :: Only
Classifier: Topic :: Scientific/Engineering
Requires-Python: >=3.5
License-File: LICENSE
Requires-Dist: ezdxf
Requires-Dist: numpy
Requires-Dist: shapely
Requires-Dist: geomdl
Provides-Extra: dev
Requires-Dist: matplotlib; extra == "dev"
Requires-Dist: pytest; extra == "dev"
